setup.py
bigsky/__init__.py
bigsky.egg-info/PKG-INFO
bigsky.egg-info/SOURCES.txt
bigsky.egg-info/dependency_links.txt
bigsky.egg-info/requires.txt
bigsky.egg-info/top_level.txt
bigsky.egg-info/zip-safe
bigsky/exif/__init__.py
bigsky/inputs/__init__.py
bigsky/inputs/flickr.py
bigsky/inputs/reader.py
bigsky/outputs/__init__.py
bigsky/outputs/exiv2.py
bigsky/outputs/s3_import.py
bigsky/outputs/simpledb_import.py
bigsky/outputs/simpledb_output.py
bigsky/outputs/to_googlemap.py
scripts/bigsky_exif
scripts/bigsky_exiv2
scripts/bigsky_html
scripts/bigsky_s3_import
scripts/bigsky_simpledb_import
scripts/bigsky_simpledb_output
scripts/bigsky_spider