Metadata-Version: 1.0
Name: bigsky
Version: 0.0.0
Summary: WNYC's big data image processing toolkit
Home-page: http://github.com/wnyc/bigsky
Author: Adam DePrince
Author-email: adeprince@nypublicradio.org
License: MIT
Platform: UNKNOWN
